featree/__init__.py
featree/config.py
featree/llm.py
featree/relation.py
featree/tree.py
featree-0.2.6.dist-info/LICENSE
featree-0.2.6.dist-info/METADATA
featree-0.2.6.dist-info/WHEEL
featree-0.2.6.dist-info/RECORD
